README
setup.cfg
setup.py
APNSWrapper/__init__.py
HypnoAPNSWrapper.egg-info/PKG-INFO
HypnoAPNSWrapper.egg-info/SOURCES.txt
HypnoAPNSWrapper.egg-info/dependency_links.txt
HypnoAPNSWrapper.egg-info/requires.txt
HypnoAPNSWrapper.egg-info/top_level.txt