Metadata-Version: 1.0
Name: HypnoAPNSWrapper
Version: 0.3-4
Summary: This is wrapper for Apple Push Notification Service.
Home-page: http://code.google.com/p/apns-python-wrapper/
Author: Max Klymyshyn, Sonettic, Jan Huelsbergen
Author-email: klymyshyn@gmail.com
License: ALv2
Keywords: apns push notification service wrapper apple
Platform: UNKNOWN
Classifier: Intended Audience :: Customer Service
Classifier: Topic :: Internet
